formless/__init__.py
formless-0.9.0.dist-info/METADATA
formless-0.9.0.dist-info/WHEEL
formless-0.9.0.dist-info/entry_points.txt
formless-0.9.0.dist-info/licenses/LICENSE
formless-0.9.0.dist-info/RECORD
