Metadata-Version: 2.4
Name: formless
Version: 0.9.0
Summary: Handwritten + image OCR.
License-File: LICENSE
Requires-Python: >=3.12
Requires-Dist: accelerate>=1.2.1
Requires-Dist: alembic>=1.14.0
Requires-Dist: autoawq>=0.2.7.post3
Requires-Dist: bitsandbytes>=0.45.1
Requires-Dist: blobfile>=3.0.0
Requires-Dist: boto>=2.49.0
Requires-Dist: datasketch>=1.6.5
Requires-Dist: deepspeed>=0.16.3
Requires-Dist: editables>=0.5
Requires-Dist: fastapi>=0.115.6
Requires-Dist: flash-attn>=2.7.4.post1
Requires-Dist: hatchling>=1.22.5
Requires-Dist: hf-transfer>=0.1.8
Requires-Dist: huggingface-hub[hf-transfer]>=0.27.1
Requires-Dist: imagehash>=4.3.2
Requires-Dist: jiwer>=3.1.0
Requires-Dist: lark-parser>=0.12.0
Requires-Dist: modal>=0.64.178
Requires-Dist: more-itertools>=10.6.0
Requires-Dist: ninja>=1.11.1
Requires-Dist: outlines>=0.1.11
Requires-Dist: packaging>=23.1
Requires-Dist: pandas>=2.2.3
Requires-Dist: pillow>=10.4.0
Requires-Dist: pre-commit>=4.0.1
Requires-Dist: psycopg2-binary>=2.9.10
Requires-Dist: psycopg2>=2.9.10
Requires-Dist: pycairo>=1.27.0
Requires-Dist: pydantic>=2.10.4
Requires-Dist: python-dotenv>=1.0.1
Requires-Dist: python-fasthtml>=0.12.1
Requires-Dist: python-magic>=0.4.27
Requires-Dist: requests>=2.32.3
Requires-Dist: s3fs>=2024.9.0
Requires-Dist: safetensors>=0.5.1
Requires-Dist: sentencepiece>=0.2.0
Requires-Dist: simpleicons>=7.21.0
Requires-Dist: sqlite-minutils>=4.0.3
Requires-Dist: sqlmodel>=0.0.22
Requires-Dist: starlette>=0.46.1
Requires-Dist: stripe>=11.5.0
Requires-Dist: term-image>=0.7.2
Requires-Dist: tiktoken>=0.7.0
Requires-Dist: timm>=1.0.14
Requires-Dist: torch>=2.5.1
Requires-Dist: torchao>=0.7.0
Requires-Dist: torchvision>=0.20.1
Requires-Dist: tqdm>=4.67.1
Requires-Dist: transformers>=4.48.2
Requires-Dist: validators>=0.34.0
Requires-Dist: vllm>=0.7.1
Requires-Dist: wandb>=0.19.4
Requires-Dist: wheel>=0.45.1
